komodo/README.md
komodo/__init__.py
komodo/config.py
komodo/core/agents/chatdoc_agent.py
komodo/core/agents/collection_builder.py
komodo/core/agents/coordinator_agent.py
komodo/core/agents/default.py
komodo/core/agents/difference_agent.py
komodo/core/agents/echo_agent.py
komodo/core/agents/elastic_agent.py
komodo/core/agents/groot_agent.py
komodo/core/agents/librarian_agent.py
komodo/core/agents/mongo_agent.py
komodo/core/agents/pdf_generator.py
komodo/core/agents/sample_agent.py
komodo/core/agents/summarizer_agent.py
komodo/core/agents/translator_agent.py
komodo/core/agents/widget_builder_agent.py
komodo/core/sources/filesystem.py
komodo/core/sources/s3bucketkey.py
komodo/core/sources/webpages.py
komodo/core/sources/website_crawler.py
komodo/core/tools/elastic/elastic_connect.py
komodo/core/tools/elastic/elastic_count.py
komodo/core/tools/elastic/elastic_get.py
komodo/core/tools/elastic/elastic_search.py
komodo/core/tools/files/collection_builder.py
komodo/core/tools/files/collection_lister.py
komodo/core/tools/files/collection_reader.py
komodo/core/tools/files/directory_reader.py
komodo/core/tools/files/file_reader.py
komodo/core/tools/files/file_writer.py
komodo/core/tools/markets/polygon_search.py
komodo/core/tools/mongo/mongo_connect.py
komodo/core/tools/mongo/mongo_databases.py
komodo/core/tools/mongo/mongo_query.py
komodo/core/tools/mongo/mongo_schema.py
komodo/core/tools/mongo/mongo_unique.py
komodo/core/tools/search/vector_search.py
komodo/core/tools/search/vector_search_runtime.py
komodo/core/tools/utils/agent_tool.py
komodo/core/tools/utils/sample_tool.py
komodo/core/tools/utils/thought_tool.py
komodo/core/tools/utils/workflow_tool.py
komodo/core/tools/web/data_fetcher.py
komodo/core/tools/web/serpapi_search.py
komodo/core/tools/web/tavily_search.py
komodo/core/tools/web/web_scraper.py
komodo/core/utils/agent_helper.py
komodo/core/utils/indexer.py
komodo/core/utils/play.py
komodo/core/utils/rag_context.py
komodo/core/vector_stores/pinecone_store.py
komodo_sdk-0.1.4.dist-info/METADATA
komodo_sdk-0.1.4.dist-info/WHEEL
komodo_sdk-0.1.4.dist-info/RECORD
