Metadata-Version: 2.3
Name: komodo-sdk
Version: 0.1.4
Summary: Komodo SDK
Project-URL: Homepage, https://github.com/Komodo-AI/komodo-sdk.git
Author-email: Ryan Oberoi <ryan.oberoi@komodoapp.ai>
Classifier: Operating System :: OS Independent
Classifier: Programming Language :: Python :: 3
Requires-Python: >=3.9
Requires-Dist: aiofiles~=23.2.1
Requires-Dist: beautifulsoup4~=4.8.0
Requires-Dist: boto3~=1.33.6
Requires-Dist: botocore~=1.33.6
Requires-Dist: celery~=5.4.0
Requires-Dist: dash-bootstrap-components~=1.5.0
Requires-Dist: dash-chart-editor
Requires-Dist: dash~=2.16.1
Requires-Dist: elastic-transport==8.12.0
Requires-Dist: elasticsearch==7.16.1
Requires-Dist: fastapi~=0.109.2
Requires-Dist: firebase-admin~=6.5.0
Requires-Dist: ftfy~=6.1.3
Requires-Dist: google-search-results~=2.4.2
Requires-Dist: gunicorn~=21.2.0
Requires-Dist: html2text~=2020.1.16
Requires-Dist: html5lib~=1.1
Requires-Dist: humanfriendly~=10.0
Requires-Dist: inflection~=0.5.1
Requires-Dist: jupyter~=1.0.0
Requires-Dist: langchain-community~=0.0.17
Requires-Dist: langchain-core~=0.1.18
Requires-Dist: langchain-openai~=0.0.8
Requires-Dist: langchain~=0.1.12
Requires-Dist: markdown2~=2.4.0
Requires-Dist: nltk~=3.8.1
Requires-Dist: openai~=1.14.3
Requires-Dist: openpyxl~=3.1.2
Requires-Dist: pandas~=2.1.3
Requires-Dist: paradag~=1.2.0
Requires-Dist: pdfkit~=1.0.0
Requires-Dist: pinecone-client~=3.1.0
Requires-Dist: plotly~=5.20.0
Requires-Dist: pymongo~=4.6.2
Requires-Dist: pyodbc~=5.1.0
Requires-Dist: pypdf2~=3.0.1
Requires-Dist: pypdf~=4.1.0
Requires-Dist: pytest-xdist~=2.4.0
Requires-Dist: pytest~=7.4.3
Requires-Dist: python-magic~=0.4.27
Requires-Dist: python-multipart~=0.0.9
Requires-Dist: qdrant-client~=1.7.2
Requires-Dist: redis~=5.0.1
Requires-Dist: requests~=2.31.0
Requires-Dist: sentry-sdk~=1.38.0
Requires-Dist: serpapi~=0.1.5
Requires-Dist: stripe~=8.10.0
Requires-Dist: termcolor~=2.4.0
Requires-Dist: textract~=1.6.5
Requires-Dist: unidecode~=1.3.2
Requires-Dist: urlextract~=1.8.0
Requires-Dist: urllib3~=1.26.18
Requires-Dist: uvicorn~=0.27.1
Requires-Dist: watchdog~=4.0.0
Requires-Dist: werkzeug~=3.0.1
Requires-Dist: wkhtmltopdf~=0.2
